django_scaleway_email/__init__.py
django_scaleway_email/apps.py
django_scaleway_email/backend.py
django_scaleway_email-0.1.1.dist-info/METADATA
django_scaleway_email-0.1.1.dist-info/WHEEL
django_scaleway_email-0.1.1.dist-info/RECORD
