Metadata-Version: 2.4
Name: django-scaleway-email
Version: 0.1.1
Summary: Django email backend for Scaleway Transactional Email service
License: MIT
Author: Julian Wachholz
Author-email: julian@wachholz.ch
Requires-Python: >=3.8,<4.0
Classifier: License :: OSI Approved :: MIT License
Classifier: Programming Language :: Python :: 3
Classifier: Programming Language :: Python :: 3.8
Classifier: Programming Language :: Python :: 3.9
Classifier: Programming Language :: Python :: 3.10
Classifier: Programming Language :: Python :: 3.11
Classifier: Programming Language :: Python :: 3.12
Classifier: Programming Language :: Python :: 3.13
Classifier: Programming Language :: Python :: 3.14
Requires-Dist: requests (>=2.0.0)
